AUTHORS
LICENSE.txt
MANIFEST.in
NEWS.txt
README.rst
setup.py
src/etcd_gevent/__init__.py
src/etcd_gevent/auth.py
src/etcd_gevent/client.py
src/etcd_gevent/lock.py
src/etcd_gevent.egg-info/PKG-INFO
src/etcd_gevent.egg-info/SOURCES.txt
src/etcd_gevent.egg-info/dependency_links.txt
src/etcd_gevent.egg-info/not-zip-safe
src/etcd_gevent.egg-info/requires.txt
src/etcd_gevent.egg-info/top_level.txt
src/etcd_gevent/tests/__init__.py
src/etcd_gevent/tests/test_auth.py
src/etcd_gevent/tests/integration/__init__.py
src/etcd_gevent/tests/integration/helpers.py
src/etcd_gevent/tests/integration/test_simple.py
src/etcd_gevent/tests/integration/test_ssl.py
src/etcd_gevent/tests/unit/__init__.py
src/etcd_gevent/tests/unit/test_client.py
src/etcd_gevent/tests/unit/test_lock.py
src/etcd_gevent/tests/unit/test_old_request.py
src/etcd_gevent/tests/unit/test_request.py
src/etcd_gevent/tests/unit/test_result.py