Metadata-Version: 1.1
Name: etcd-gevent
Version: 0.1.1
Summary: A python client for etcd
Home-page: http://github.com/wjsi/etcd-gevent
Author: Wenjun Si
Author-email: swj0066@gmail.com
License: MIT
Keywords: async etcd raft distributed log api client
Platform: UNKNOWN
Classifier: Topic :: System :: Distributed Computing
Classifier: Topic :: Software Development :: Libraries
Classifier: License :: OSI Approved :: MIT License
Classifier: Programming Language :: Python :: 2
Classifier: Programming Language :: Python :: 3
Classifier: Topic :: Database :: Front-Ends
